[
  {
    "timestamp": "2026-06-06T14:27:30+00:00",
    "status": "up"
  },
  {
    "timestamp": "2026-06-06T13:53:48+00:00",
    "status": "up"
  },
  {
    "timestamp": "2026-06-06T13:12:19+00:00",
    "status": "up"
  },
  {
    "timestamp": "2026-06-06T12:43:07+00:00",
    "status": "up"
  },
  {
    "timestamp": "2026-06-06T12:07:48+00:00",
    "status": "up"
  },
  {
    "timestamp": "2026-06-06T11:41:49+00:00",
    "status": "up"
  },
  {
    "timestamp": "2026-06-06T11:05:49+00:00",
    "status": "up"
  },
  {
    "timestamp": "2026-06-06T10:31:52+00:00",
    "status": "up"
  },
  {
    "timestamp": "2026-06-06T09:49:28+00:00",
    "status": "up"
  },
  {
    "timestamp": "2026-06-06T09:06:52+00:00",
    "status": "up"
  },
  {
    "timestamp": "2026-06-06T08:10:49+00:00",
    "status": "up"
  },
  {
    "timestamp": "2026-06-06T07:17:26+00:00",
    "status": "up"
  }
]
