[
  {
    "timestamp": "2025-11-17T22:58:11+00:00",
    "status": "up"
  },
  {
    "timestamp": "2025-11-17T22:52:19+00:00",
    "status": "up"
  },
  {
    "timestamp": "2025-11-17T22:46:18+00:00",
    "status": "up"
  },
  {
    "timestamp": "2025-11-17T22:39:29+00:00",
    "status": "up"
  },
  {
    "timestamp": "2025-11-17T22:30:53+00:00",
    "status": "up"
  },
  {
    "timestamp": "2025-11-17T22:19:04+00:00",
    "status": "up"
  },
  {
    "timestamp": "2025-11-17T22:08:40+00:00",
    "status": "up"
  },
  {
    "timestamp": "2025-11-17T21:59:38+00:00",
    "status": "up"
  },
  {
    "timestamp": "2025-11-17T21:54:04+00:00",
    "status": "up"
  },
  {
    "timestamp": "2025-11-17T21:48:21+00:00",
    "status": "up"
  },
  {
    "timestamp": "2025-11-17T21:42:15+00:00",
    "status": "up"
  },
  {
    "timestamp": "2025-11-17T21:35:01+00:00",
    "status": "up"
  }
]
