[
  {
    "timestamp": "2025-12-06T22:02:15+00:00",
    "status": "up"
  },
  {
    "timestamp": "2025-12-06T21:55:30+00:00",
    "status": "up"
  },
  {
    "timestamp": "2025-12-06T21:49:32+00:00",
    "status": "up"
  },
  {
    "timestamp": "2025-12-06T21:43:50+00:00",
    "status": "up"
  },
  {
    "timestamp": "2025-12-06T21:38:06+00:00",
    "status": "up"
  },
  {
    "timestamp": "2025-12-06T21:31:19+00:00",
    "status": "up"
  },
  {
    "timestamp": "2025-12-06T21:24:20+00:00",
    "status": "up"
  },
  {
    "timestamp": "2025-12-06T21:14:01+00:00",
    "status": "up"
  },
  {
    "timestamp": "2025-12-06T21:04:41+00:00",
    "status": "up"
  },
  {
    "timestamp": "2025-12-06T20:57:04+00:00",
    "status": "up"
  },
  {
    "timestamp": "2025-12-06T20:51:08+00:00",
    "status": "up"
  },
  {
    "timestamp": "2025-12-06T20:45:01+00:00",
    "status": "up"
  }
]
