[
  {
    "timestamp": "2026-01-31T07:33:31+00:00",
    "status": "up"
  },
  {
    "timestamp": "2026-01-31T07:18:42+00:00",
    "status": "up"
  },
  {
    "timestamp": "2026-01-31T07:06:37+00:00",
    "status": "up"
  },
  {
    "timestamp": "2026-01-31T06:53:54+00:00",
    "status": "up"
  },
  {
    "timestamp": "2026-01-31T06:33:14+00:00",
    "status": "up"
  },
  {
    "timestamp": "2026-01-31T06:17:23+00:00",
    "status": "up"
  },
  {
    "timestamp": "2026-01-31T05:58:29+00:00",
    "status": "up"
  },
  {
    "timestamp": "2026-01-31T05:44:37+00:00",
    "status": "up"
  },
  {
    "timestamp": "2026-01-31T05:26:27+00:00",
    "status": "up"
  },
  {
    "timestamp": "2026-01-31T05:07:56+00:00",
    "status": "up"
  },
  {
    "timestamp": "2026-01-31T04:45:07+00:00",
    "status": "up"
  },
  {
    "timestamp": "2026-01-31T04:13:34+00:00",
    "status": "up"
  }
]
