[
  {
    "timestamp": "2025-06-20T19:04:35+00:00",
    "status": "up"
  },
  {
    "timestamp": "2025-06-20T18:57:15+00:00",
    "status": "up"
  },
  {
    "timestamp": "2025-06-20T18:50:35+00:00",
    "status": "up"
  },
  {
    "timestamp": "2025-06-20T18:40:44+00:00",
    "status": "up"
  },
  {
    "timestamp": "2025-06-20T18:27:00+00:00",
    "status": "up"
  },
  {
    "timestamp": "2025-06-20T18:13:53+00:00",
    "status": "up"
  },
  {
    "timestamp": "2025-06-20T18:03:49+00:00",
    "status": "up"
  },
  {
    "timestamp": "2025-06-20T17:55:53+00:00",
    "status": "up"
  },
  {
    "timestamp": "2025-06-20T17:49:54+00:00",
    "status": "up"
  },
  {
    "timestamp": "2025-06-20T17:44:17+00:00",
    "status": "up"
  },
  {
    "timestamp": "2025-06-20T17:36:55+00:00",
    "status": "up"
  },
  {
    "timestamp": "2025-06-20T17:28:07+00:00",
    "status": "up"
  }
]
