[
  {
    "timestamp": "2025-08-08T10:41:51+00:00",
    "status": "up"
  },
  {
    "timestamp": "2025-08-08T10:28:21+00:00",
    "status": "up"
  },
  {
    "timestamp": "2025-08-08T10:15:29+00:00",
    "status": "up"
  },
  {
    "timestamp": "2025-08-08T10:05:22+00:00",
    "status": "up"
  },
  {
    "timestamp": "2025-08-08T09:56:49+00:00",
    "status": "up"
  },
  {
    "timestamp": "2025-08-08T09:49:34+00:00",
    "status": "up"
  },
  {
    "timestamp": "2025-08-08T09:39:18+00:00",
    "status": "up"
  },
  {
    "timestamp": "2025-08-08T09:25:38+00:00",
    "status": "up"
  },
  {
    "timestamp": "2025-08-08T09:12:51+00:00",
    "status": "up"
  },
  {
    "timestamp": "2025-08-08T09:00:35+00:00",
    "status": "up"
  },
  {
    "timestamp": "2025-08-08T08:51:17+00:00",
    "status": "up"
  },
  {
    "timestamp": "2025-08-08T08:39:27+00:00",
    "status": "up"
  }
]
