[
  {
    "timestamp": "2026-04-19T07:55:04+00:00",
    "status": "up"
  },
  {
    "timestamp": "2026-04-19T07:25:44+00:00",
    "status": "up"
  },
  {
    "timestamp": "2026-04-19T06:53:35+00:00",
    "status": "up"
  },
  {
    "timestamp": "2026-04-19T06:17:35+00:00",
    "status": "up"
  },
  {
    "timestamp": "2026-04-19T05:40:30+00:00",
    "status": "up"
  },
  {
    "timestamp": "2026-04-19T04:53:47+00:00",
    "status": "up"
  },
  {
    "timestamp": "2026-04-19T03:52:14+00:00",
    "status": "up"
  },
  {
    "timestamp": "2026-04-19T02:39:06+00:00",
    "status": "up"
  },
  {
    "timestamp": "2026-04-19T01:41:47+00:00",
    "status": "up"
  },
  {
    "timestamp": "2026-04-19T01:02:01+00:00",
    "status": "up"
  },
  {
    "timestamp": "2026-04-19T00:02:55+00:00",
    "status": "up"
  },
  {
    "timestamp": "2026-04-18T23:50:33+00:00",
    "status": "up"
  }
]
