[
  {
    "timestamp": "2025-10-12T15:59:26+00:00",
    "status": "up"
  },
  {
    "timestamp": "2025-10-12T15:53:38+00:00",
    "status": "up"
  },
  {
    "timestamp": "2025-10-12T15:47:25+00:00",
    "status": "up"
  },
  {
    "timestamp": "2025-10-12T15:41:21+00:00",
    "status": "up"
  },
  {
    "timestamp": "2025-10-12T15:35:14+00:00",
    "status": "up"
  },
  {
    "timestamp": "2025-10-12T15:28:49+00:00",
    "status": "up"
  },
  {
    "timestamp": "2025-10-12T15:21:20+00:00",
    "status": "up"
  },
  {
    "timestamp": "2025-10-12T15:10:54+00:00",
    "status": "up"
  },
  {
    "timestamp": "2025-10-12T15:02:13+00:00",
    "status": "up"
  },
  {
    "timestamp": "2025-10-12T14:55:39+00:00",
    "status": "up"
  },
  {
    "timestamp": "2025-10-12T14:50:00+00:00",
    "status": "up"
  },
  {
    "timestamp": "2025-10-12T14:43:58+00:00",
    "status": "up"
  }
]
