[
  {
    "timestamp": "2025-11-20T19:38:05+00:00",
    "status": "up"
  },
  {
    "timestamp": "2025-11-20T19:31:23+00:00",
    "status": "up"
  },
  {
    "timestamp": "2025-11-20T19:25:12+00:00",
    "status": "up"
  },
  {
    "timestamp": "2025-11-20T19:16:27+00:00",
    "status": "up"
  },
  {
    "timestamp": "2025-11-20T19:06:52+00:00",
    "status": "up"
  },
  {
    "timestamp": "2025-11-20T18:58:39+00:00",
    "status": "up"
  },
  {
    "timestamp": "2025-11-20T18:51:38+00:00",
    "status": "up"
  },
  {
    "timestamp": "2025-11-20T18:40:56+00:00",
    "status": "up"
  },
  {
    "timestamp": "2025-11-20T18:25:18+00:00",
    "status": "up"
  },
  {
    "timestamp": "2025-11-20T18:12:15+00:00",
    "status": "up"
  },
  {
    "timestamp": "2025-11-20T17:59:13+00:00",
    "status": "up"
  },
  {
    "timestamp": "2025-11-20T17:53:26+00:00",
    "status": "up"
  }
]
