[
  {
    "timestamp": "2025-06-15T17:42:44+00:00",
    "status": "up"
  },
  {
    "timestamp": "2025-06-15T17:35:42+00:00",
    "status": "up"
  },
  {
    "timestamp": "2025-06-15T17:27:29+00:00",
    "status": "up"
  },
  {
    "timestamp": "2025-06-15T17:17:17+00:00",
    "status": "up"
  },
  {
    "timestamp": "2025-06-15T17:07:40+00:00",
    "status": "up"
  },
  {
    "timestamp": "2025-06-15T16:59:33+00:00",
    "status": "up"
  },
  {
    "timestamp": "2025-06-15T16:53:43+00:00",
    "status": "up"
  },
  {
    "timestamp": "2025-06-15T16:46:15+00:00",
    "status": "up"
  },
  {
    "timestamp": "2025-06-15T16:36:39+00:00",
    "status": "up"
  },
  {
    "timestamp": "2025-06-15T16:24:45+00:00",
    "status": "up"
  },
  {
    "timestamp": "2025-06-15T16:12:41+00:00",
    "status": "up"
  },
  {
    "timestamp": "2025-06-15T16:03:10+00:00",
    "status": "up"
  }
]
