[
  {
    "timestamp": "2025-10-26T23:29:54+00:00",
    "status": "up"
  },
  {
    "timestamp": "2025-10-26T23:21:53+00:00",
    "status": "up"
  },
  {
    "timestamp": "2025-10-26T23:11:12+00:00",
    "status": "up"
  },
  {
    "timestamp": "2025-10-26T23:02:19+00:00",
    "status": "up"
  },
  {
    "timestamp": "2025-10-26T22:55:28+00:00",
    "status": "up"
  },
  {
    "timestamp": "2025-10-26T22:49:33+00:00",
    "status": "up"
  },
  {
    "timestamp": "2025-10-26T22:43:33+00:00",
    "status": "up"
  },
  {
    "timestamp": "2025-10-26T22:36:51+00:00",
    "status": "up"
  },
  {
    "timestamp": "2025-10-26T22:28:52+00:00",
    "status": "up"
  },
  {
    "timestamp": "2025-10-26T22:18:00+00:00",
    "status": "up"
  },
  {
    "timestamp": "2025-10-26T22:07:53+00:00",
    "status": "up"
  },
  {
    "timestamp": "2025-10-26T21:59:35+00:00",
    "status": "up"
  }
]
