[
  {
    "timestamp": "2025-11-21T12:27:52+00:00",
    "status": "up"
  },
  {
    "timestamp": "2025-11-21T12:13:30+00:00",
    "status": "up"
  },
  {
    "timestamp": "2025-11-21T11:58:21+00:00",
    "status": "up"
  },
  {
    "timestamp": "2025-11-21T11:52:30+00:00",
    "status": "up"
  },
  {
    "timestamp": "2025-11-21T11:46:40+00:00",
    "status": "up"
  },
  {
    "timestamp": "2025-11-21T11:40:52+00:00",
    "status": "up"
  },
  {
    "timestamp": "2025-11-21T11:34:31+00:00",
    "status": "up"
  },
  {
    "timestamp": "2025-11-21T11:27:42+00:00",
    "status": "up"
  },
  {
    "timestamp": "2025-11-21T11:19:33+00:00",
    "status": "up"
  },
  {
    "timestamp": "2025-11-21T11:09:28+00:00",
    "status": "up"
  },
  {
    "timestamp": "2025-11-21T11:00:44+00:00",
    "status": "up"
  },
  {
    "timestamp": "2025-11-21T10:54:39+00:00",
    "status": "up"
  }
]
