[
  {
    "timestamp": "2025-06-15T15:50:08+00:00",
    "status": "up"
  },
  {
    "timestamp": "2025-06-15T15:43:40+00:00",
    "status": "up"
  },
  {
    "timestamp": "2025-06-15T15:35:49+00:00",
    "status": "up"
  },
  {
    "timestamp": "2025-06-15T15:27:01+00:00",
    "status": "up"
  },
  {
    "timestamp": "2025-06-15T15:16:46+00:00",
    "status": "up"
  },
  {
    "timestamp": "2025-06-15T15:06:55+00:00",
    "status": "up"
  },
  {
    "timestamp": "2025-06-15T14:58:35+00:00",
    "status": "up"
  },
  {
    "timestamp": "2025-06-15T14:52:56+00:00",
    "status": "up"
  },
  {
    "timestamp": "2025-06-15T14:46:57+00:00",
    "status": "up"
  },
  {
    "timestamp": "2025-06-15T14:40:39+00:00",
    "status": "up"
  },
  {
    "timestamp": "2025-06-15T14:33:08+00:00",
    "status": "up"
  },
  {
    "timestamp": "2025-06-15T14:24:02+00:00",
    "status": "up"
  }
]
