[
  {
    "timestamp": "2026-04-05T23:18:05+00:00",
    "status": "up"
  },
  {
    "timestamp": "2026-04-05T23:04:30+00:00",
    "status": "up"
  },
  {
    "timestamp": "2026-04-05T22:53:54+00:00",
    "status": "up"
  },
  {
    "timestamp": "2026-04-05T22:38:47+00:00",
    "status": "up"
  },
  {
    "timestamp": "2026-04-05T22:22:27+00:00",
    "status": "up"
  },
  {
    "timestamp": "2026-04-05T22:10:00+00:00",
    "status": "up"
  },
  {
    "timestamp": "2026-04-05T21:57:29+00:00",
    "status": "up"
  },
  {
    "timestamp": "2026-04-05T21:46:13+00:00",
    "status": "up"
  },
  {
    "timestamp": "2026-04-05T21:31:26+00:00",
    "status": "up"
  },
  {
    "timestamp": "2026-04-05T21:16:51+00:00",
    "status": "up"
  },
  {
    "timestamp": "2026-04-05T21:03:58+00:00",
    "status": "up"
  },
  {
    "timestamp": "2026-04-05T20:53:38+00:00",
    "status": "up"
  }
]
