[
  {
    "timestamp": "2025-06-05T19:07:45+00:00",
    "status": "up"
  },
  {
    "timestamp": "2025-06-05T18:59:31+00:00",
    "status": "up"
  },
  {
    "timestamp": "2025-06-05T18:53:39+00:00",
    "status": "up"
  },
  {
    "timestamp": "2025-06-05T18:50:49+00:00",
    "status": "up"
  },
  {
    "timestamp": "2025-06-05T17:49:43+00:00",
    "status": "up"
  },
  {
    "timestamp": "2025-06-05T17:43:59+00:00",
    "status": "up"
  },
  {
    "timestamp": "2025-06-05T17:38:04+00:00",
    "status": "up"
  },
  {
    "timestamp": "2025-06-05T17:31:59+00:00",
    "status": "up"
  },
  {
    "timestamp": "2025-06-05T17:25:37+00:00",
    "status": "up"
  },
  {
    "timestamp": "2025-06-05T17:16:42+00:00",
    "status": "up"
  },
  {
    "timestamp": "2025-06-05T17:07:31+00:00",
    "status": "up"
  },
  {
    "timestamp": "2025-06-05T16:59:30+00:00",
    "status": "up"
  }
]
