[
  {
    "timestamp": "2025-10-13T03:34:41+00:00",
    "status": "up"
  },
  {
    "timestamp": "2025-10-13T03:16:37+00:00",
    "status": "up"
  },
  {
    "timestamp": "2025-10-13T02:51:11+00:00",
    "status": "up"
  },
  {
    "timestamp": "2025-10-13T02:18:58+00:00",
    "status": "up"
  },
  {
    "timestamp": "2025-10-13T01:40:37+00:00",
    "status": "up"
  },
  {
    "timestamp": "2025-10-13T01:02:57+00:00",
    "status": "up"
  },
  {
    "timestamp": "2025-10-13T00:36:41+00:00",
    "status": "up"
  },
  {
    "timestamp": "2025-10-12T23:59:41+00:00",
    "status": "up"
  },
  {
    "timestamp": "2025-10-12T23:53:56+00:00",
    "status": "up"
  },
  {
    "timestamp": "2025-10-12T23:48:09+00:00",
    "status": "up"
  },
  {
    "timestamp": "2025-10-12T23:41:58+00:00",
    "status": "up"
  },
  {
    "timestamp": "2025-10-12T23:36:22+00:00",
    "status": "up"
  }
]
