[
  {
    "timestamp": "2026-04-13T09:47:25+00:00",
    "status": "up"
  },
  {
    "timestamp": "2026-04-13T09:06:33+00:00",
    "status": "up"
  },
  {
    "timestamp": "2026-04-13T08:22:23+00:00",
    "status": "up"
  },
  {
    "timestamp": "2026-04-13T07:35:29+00:00",
    "status": "up"
  },
  {
    "timestamp": "2026-04-13T06:56:19+00:00",
    "status": "up"
  },
  {
    "timestamp": "2026-04-13T05:58:13+00:00",
    "status": "up"
  },
  {
    "timestamp": "2026-04-13T05:01:22+00:00",
    "status": "up"
  },
  {
    "timestamp": "2026-04-13T03:55:33+00:00",
    "status": "up"
  },
  {
    "timestamp": "2026-04-13T02:41:36+00:00",
    "status": "up"
  },
  {
    "timestamp": "2026-04-13T01:43:31+00:00",
    "status": "up"
  },
  {
    "timestamp": "2026-04-13T01:01:06+00:00",
    "status": "up"
  },
  {
    "timestamp": "2026-04-13T00:03:28+00:00",
    "status": "up"
  }
]
