[
  {
    "timestamp": "2025-08-01T13:00:26+00:00",
    "status": "up"
  },
  {
    "timestamp": "2025-08-01T12:37:27+00:00",
    "status": "up"
  },
  {
    "timestamp": "2025-08-01T12:20:29+00:00",
    "status": "up"
  },
  {
    "timestamp": "2025-08-01T12:08:11+00:00",
    "status": "up"
  },
  {
    "timestamp": "2025-08-01T11:56:41+00:00",
    "status": "up"
  },
  {
    "timestamp": "2025-08-01T11:50:52+00:00",
    "status": "up"
  },
  {
    "timestamp": "2025-08-01T11:44:33+00:00",
    "status": "up"
  },
  {
    "timestamp": "2025-08-01T11:36:53+00:00",
    "status": "up"
  },
  {
    "timestamp": "2025-08-01T11:28:35+00:00",
    "status": "up"
  },
  {
    "timestamp": "2025-08-01T11:18:27+00:00",
    "status": "up"
  },
  {
    "timestamp": "2025-08-01T11:08:07+00:00",
    "status": "up"
  },
  {
    "timestamp": "2025-08-01T10:59:08+00:00",
    "status": "up"
  }
]
