[
  {
    "timestamp": "2025-10-12T10:39:39+00:00",
    "status": "up"
  },
  {
    "timestamp": "2025-10-12T10:32:34+00:00",
    "status": "up"
  },
  {
    "timestamp": "2025-10-12T10:24:05+00:00",
    "status": "up"
  },
  {
    "timestamp": "2025-10-12T10:12:46+00:00",
    "status": "up"
  },
  {
    "timestamp": "2025-10-12T10:03:32+00:00",
    "status": "up"
  },
  {
    "timestamp": "2025-10-12T09:56:09+00:00",
    "status": "up"
  },
  {
    "timestamp": "2025-10-12T09:50:17+00:00",
    "status": "up"
  },
  {
    "timestamp": "2025-10-12T09:44:34+00:00",
    "status": "up"
  },
  {
    "timestamp": "2025-10-12T09:38:35+00:00",
    "status": "up"
  },
  {
    "timestamp": "2025-10-12T09:32:02+00:00",
    "status": "up"
  },
  {
    "timestamp": "2025-10-12T09:25:43+00:00",
    "status": "up"
  },
  {
    "timestamp": "2025-10-12T09:16:59+00:00",
    "status": "up"
  }
]
