[
  {
    "timestamp": "2025-10-11T05:22:01+00:00",
    "status": "up"
  },
  {
    "timestamp": "2025-10-11T05:11:16+00:00",
    "status": "up"
  },
  {
    "timestamp": "2025-10-11T05:02:20+00:00",
    "status": "up"
  },
  {
    "timestamp": "2025-10-11T04:55:30+00:00",
    "status": "up"
  },
  {
    "timestamp": "2025-10-11T04:49:52+00:00",
    "status": "up"
  },
  {
    "timestamp": "2025-10-11T04:44:09+00:00",
    "status": "up"
  },
  {
    "timestamp": "2025-10-11T04:37:25+00:00",
    "status": "up"
  },
  {
    "timestamp": "2025-10-11T04:28:27+00:00",
    "status": "up"
  },
  {
    "timestamp": "2025-10-11T04:16:10+00:00",
    "status": "up"
  },
  {
    "timestamp": "2025-10-11T04:05:55+00:00",
    "status": "up"
  },
  {
    "timestamp": "2025-10-11T03:57:02+00:00",
    "status": "up"
  },
  {
    "timestamp": "2025-10-11T03:50:59+00:00",
    "status": "up"
  }
]
