[
  {
    "timestamp": "2026-01-29T16:37:10+00:00",
    "status": "up"
  },
  {
    "timestamp": "2026-01-29T16:19:50+00:00",
    "status": "up"
  },
  {
    "timestamp": "2026-01-29T16:00:19+00:00",
    "status": "up"
  },
  {
    "timestamp": "2026-01-29T15:45:42+00:00",
    "status": "up"
  },
  {
    "timestamp": "2026-01-29T15:27:20+00:00",
    "status": "up"
  },
  {
    "timestamp": "2026-01-29T15:12:47+00:00",
    "status": "up"
  },
  {
    "timestamp": "2026-01-29T14:56:34+00:00",
    "status": "up"
  },
  {
    "timestamp": "2026-01-29T14:37:29+00:00",
    "status": "up"
  },
  {
    "timestamp": "2026-01-29T14:20:49+00:00",
    "status": "up"
  },
  {
    "timestamp": "2026-01-29T13:58:25+00:00",
    "status": "up"
  },
  {
    "timestamp": "2026-01-29T13:34:27+00:00",
    "status": "up"
  },
  {
    "timestamp": "2026-01-29T13:05:54+00:00",
    "status": "up"
  }
]
