[
  {
    "timestamp": "2025-08-25T19:47:30+00:00",
    "status": "up"
  },
  {
    "timestamp": "2025-08-25T19:41:28+00:00",
    "status": "up"
  },
  {
    "timestamp": "2025-08-25T19:35:17+00:00",
    "status": "up"
  },
  {
    "timestamp": "2025-08-25T19:21:59+00:00",
    "status": "up"
  },
  {
    "timestamp": "2025-08-25T19:12:14+00:00",
    "status": "up"
  },
  {
    "timestamp": "2025-08-25T19:03:33+00:00",
    "status": "up"
  },
  {
    "timestamp": "2025-08-25T18:56:33+00:00",
    "status": "up"
  },
  {
    "timestamp": "2025-08-25T18:49:19+00:00",
    "status": "up"
  },
  {
    "timestamp": "2025-08-25T18:38:29+00:00",
    "status": "up"
  },
  {
    "timestamp": "2025-08-25T18:23:35+00:00",
    "status": "up"
  },
  {
    "timestamp": "2025-08-25T18:11:06+00:00",
    "status": "up"
  },
  {
    "timestamp": "2025-08-25T17:59:22+00:00",
    "status": "up"
  }
]
