[
  {
    "timestamp": "2025-08-24T20:54:55+00:00",
    "status": "up"
  },
  {
    "timestamp": "2025-08-24T20:49:03+00:00",
    "status": "up"
  },
  {
    "timestamp": "2025-08-24T20:43:05+00:00",
    "status": "up"
  },
  {
    "timestamp": "2025-08-24T20:36:03+00:00",
    "status": "up"
  },
  {
    "timestamp": "2025-08-24T20:28:03+00:00",
    "status": "up"
  },
  {
    "timestamp": "2025-08-24T20:16:27+00:00",
    "status": "up"
  },
  {
    "timestamp": "2025-08-24T20:06:23+00:00",
    "status": "up"
  },
  {
    "timestamp": "2025-08-24T19:57:37+00:00",
    "status": "up"
  },
  {
    "timestamp": "2025-08-24T19:52:00+00:00",
    "status": "up"
  },
  {
    "timestamp": "2025-08-24T19:46:07+00:00",
    "status": "up"
  },
  {
    "timestamp": "2025-08-24T19:40:10+00:00",
    "status": "up"
  },
  {
    "timestamp": "2025-08-24T19:33:59+00:00",
    "status": "up"
  }
]
